odoo/addons/contract_delivery_zone/README.rst
odoo/addons/contract_delivery_zone/__init__.py
odoo/addons/contract_delivery_zone/__manifest__.py
odoo/addons/contract_delivery_zone/i18n/contract_delivery_zone.pot
odoo/addons/contract_delivery_zone/i18n/es.po
odoo/addons/contract_delivery_zone/i18n/it.po
odoo/addons/contract_delivery_zone/models/__init__.py
odoo/addons/contract_delivery_zone/models/contract_contract.py
odoo/addons/contract_delivery_zone/readme/CONTRIBUTORS.rst
odoo/addons/contract_delivery_zone/readme/DESCRIPTION.rst
odoo/addons/contract_delivery_zone/static/description/icon.png
odoo/addons/contract_delivery_zone/static/description/index.html
odoo/addons/contract_delivery_zone/tests/__init__.py
odoo/addons/contract_delivery_zone/tests/test_contract_delivery_zone.py
odoo/addons/contract_delivery_zone/views/contract_contract.xml
odoo14_addon_contract_delivery_zone-14.0.1.0.1.dev10.dist-info/METADATA
odoo14_addon_contract_delivery_zone-14.0.1.0.1.dev10.dist-info/WHEEL
odoo14_addon_contract_delivery_zone-14.0.1.0.1.dev10.dist-info/top_level.txt
odoo14_addon_contract_delivery_zone-14.0.1.0.1.dev10.dist-info/RECORD
