Metadata-Version: 2.1
Name: odoo14-addon-contract_delivery_zone
Version: 14.0.1.0.1.dev10
Summary: Allows to remind the delivery zone defined on the partner on contract level.
Home-page: https://github.com/OCA/contract
Author: ACSONE SA/NV,Odoo Community Association (OCA)
Author-email: support@odoo-community.org
License: AGPL-3
Classifier: Programming Language :: Python
Classifier: Framework :: Odoo
Classifier: Framework :: Odoo :: 14.0
Classifier: License :: OSI Approved :: GNU Affero General Public License v3
Requires-Python: >=3.6
Requires-Dist: odoo14-addon-contract
Requires-Dist: odoo14-addon-partner-delivery-zone
Requires-Dist: odoo<14.1dev,>=14.0a
